diresa/__init__.py
diresa/callback.py
diresa/layers.py
diresa/loss.py
diresa/models.py
diresa/toolbox.py
diresa-1.3.1.dist-info/METADATA
diresa-1.3.1.dist-info/WHEEL
diresa-1.3.1.dist-info/licenses/LICENSE
diresa-1.3.1.dist-info/RECORD
