Metadata-Version: 2.4
Name: diresa
Version: 1.3.1
Summary: Diresa - distance-regularized siamese twin autoencoder
Project-URL: Homepage, https://gitlab.com/etrovub/ai4wcm/public/diresa
Project-URL: Issues, https://gitlab.com/etrovub/ai4wcm/public/diresa/-/issues
Author-email: Geert De Paepe <geert.de.paepe@vub.be>
License-File: LICENSE
Keywords: climate,learning,machine,tensorflow,weather
Classifier: Development Status :: 4 - Beta
Classifier: Intended Audience :: Science/Research
Classifier: License :: OSI Approved :: MIT License
Classifier: Operating System :: OS Independent
Classifier: Programming Language :: Python :: 3
Classifier: Topic :: Scientific/Engineering :: Artificial Intelligence
Requires-Python: >=3.8
Requires-Dist: tensorflow>=2.12
